pymlt2/__init__.py
pymlt2-0.0.23.dist-info/METADATA
pymlt2-0.0.23.dist-info/WHEEL
pymlt2-0.0.23.dist-info/top_level.txt
pymlt2-0.0.23.dist-info/RECORD
