Metadata-Version: 2.4
Name: pymlt2
Version: 0.0.23
Summary: Python Machine Learning Toolkit
Author-email: Ben van Vliet <benvliet@icloud.com>
License: MIT
Requires-Python: >=3.7
Requires-Dist: pytest
Requires-Dist: pytest-cov
Requires-Dist: setuptools-scm
